RoInfo/__init__.py
RoInfo-0.0.6.dist-info/METADATA
RoInfo-0.0.6.dist-info/WHEEL
RoInfo-0.0.6.dist-info/top_level.txt
RoInfo-0.0.6.dist-info/RECORD
