Metadata-Version: 2.1
Name: RoInfo
Version: 0.0.6
Summary: A Roblox API Wrapper for roblox.com
Home-page: 
Author: Ryan_shamu
Author-email: Ryanshamu418@Gmail.com
Keywords: Roblox,RoInfo,Roblox Web Api,Roblox Python,Roblox For Python,Roblox Api,Roblox Api Library,Roblox Bot
Classifier: Development Status :: 5 - Production/Stable
Classifier: Intended Audience :: Developers
Classifier: Programming Language :: Python :: 3
Classifier: Operating System :: Unix
Classifier: Operating System :: MacOS :: MacOS X
Classifier: Operating System :: Microsoft :: Windows
Requires-Dist: requests
